calciumpy/__init__.py
calciumpy/address.py
calciumpy/block.py
calciumpy/block_result.py
calciumpy/command/__init__.py
calciumpy/command/assign.py
calciumpy/command/class_stmt.py
calciumpy/command/command.py
calciumpy/command/expr_stmt.py
calciumpy/command/function.py
calciumpy/command/ifs.py
calciumpy/command/import_stmt.py
calciumpy/command/loop.py
calciumpy/command/pass_stmt.py
calciumpy/element.py
calciumpy/environment.py
calciumpy/error.py
calciumpy/expression/__init__.py
calciumpy/expression/assignable.py
calciumpy/expression/call.py
calciumpy/expression/operator.py
calciumpy/index.py
calciumpy/keyword.py
calciumpy/label.py
calciumpy/namespace.py
calciumpy/parser.py
calciumpy/runtime.py
calciumpy/tool/__init__.py
calciumpy/tool/converter.py
calciumpy-0.4.3.dist-info/WHEEL
calciumpy-0.4.3.dist-info/METADATA
calciumpy-0.4.3.dist-info/RECORD
