Metadata-Version: 2.3
Name: calciumpy
Version: 0.4.3
Summary: A Calcium language interpreter
Keywords: calcium,interpreter,json
Author: Roki Turner
Author-email: Roki Turner <roki@0xcaf2.dev>
Classifier: Programming Language :: Python :: 3
Classifier: License :: OSI Approved :: MIT License
Classifier: Operating System :: OS Independent
Requires-Python: >=3.9
Project-URL: Homepage, https://github.com/0xCAF2/calciumpy
